LICENSE
MANIFEST.in
README.rst
setup.cfg
setup.py
pilight2mqtt/__init__.py
pilight2mqtt/__main__.py
pilight2mqtt/const.py
pilight2mqtt/core.py
pilight2mqtt/discover.py
pilight2mqtt.egg-info/PKG-INFO
pilight2mqtt.egg-info/SOURCES.txt
pilight2mqtt.egg-info/dependency_links.txt
pilight2mqtt.egg-info/entry_points.txt
pilight2mqtt.egg-info/not-zip-safe
pilight2mqtt.egg-info/requires.txt
pilight2mqtt.egg-info/top_level.txt